Metadata-Version: 1.0
Name: customdocs
Version: 0.3.0
Summary: Custom parsers for sphinx
Home-page: https://github.com/dabercro/customdocs
Author: Daniel Abercrombie
Author-email: dabercro@mit.edu
License: UNKNOWN
Platform: UNKNOWN
